conduit_sdk/__init__.py
conduit_sdk/block/__init__.py
conduit_sdk/block/callback_script.py
conduit_sdk/block/csv.py
conduit_sdk/block/parse.py
conduit_sdk/block/schema.py
conduit_sdk/common/__init__.py
conduit_sdk/common/schema.py
conduit_sdk/errors.py
conduit_sdk/vault.py
conduit_sdk-0.2.5.dist-info/WHEEL
conduit_sdk-0.2.5.dist-info/METADATA
conduit_sdk-0.2.5.dist-info/RECORD
