Metadata-Version: 2.1
Name: conduit-sdk
Version: 0.2.5
Summary: Conduit sdk is a collection of utils for development of conduit external block.
Author: Conduit.app
Author-email: support@getconduit.app
Requires-Python: >=3.9,<4.0
Classifier: Programming Language :: Python :: 3
Classifier: Programming Language :: Python :: 3.9
Classifier: Programming Language :: Python :: 3.10
Classifier: Programming Language :: Python :: 3.11
Requires-Dist: requests (>=2.28.1,<3.0.0)
